{
    "navbar": {
        "navbarListMain": [
            {
                "title": "მთავარი",
                "href": "/"
            },
            {
                "title": "შესახებ",
                "href": "/about_us"
            },
            {
                "title": "პროექტები",
                "href": "/projects"
            },
            {
                "title": "მაღაზია",
                "href": "/shop"
            },
            {
                "title": "დონაცია",
                "href": "/donation"
            }
        ],
        "navbarListOne": [
            {
                "id": 1,
                "title": "ისტორია",
                "href": "/about_us#one"
            },
            {
                "id": 2,
                "title": "რატომ პარსიფალი?",
                "href": "/about_us#two"
            },
            {
                "id": 3,
                "title": "ჩვენი გუნდი",
                "href": "/about_us#three"
            }
        ],
        "navbarListTwo": [
            {
                "id": 1,
                "title": "სკოლა",
                "href": "/school"
            },
            {
                "id": 2,
                "title": "სემინარი",
                "href": "/seminar"
            },
            {
                "id": 3,
                "title": "ბაღი",
                "href": "/garden"
            },
            {
                "id": 4,
                "title": "სახელოსნო",
                "href": "/workshop"
            },
            {
                "id": 5,
                "title": "რაიდთერაპია",
                "href": "/ridetherapy"
            }
        ]
    },
    "hero": {
        "text1": "ერთწლიანი კურსი",
        "text2": "პარსიფალის ახალგაზრდული სემინარი",
        "text3": "თვითშემეცნება, თვითგამორკვევა, პროფესიული ორიენტაცია",
        "text4": "გაიგე მეტი"
    },
    "about_us_main": {
        "text1": "ჩვენს შესახებ",
        "text2": "ჩვენ ვართ ახალგაზრდული საზოგადოება პარსიფალი.",
        "text3": "გზა, რომელიც ჩვენ აქამდე გავიარეთ, მოიცავს მრავალფეროვან მხატვრულ და სოციალურ აქტივობებს. პანდემიამ ბევრი სოციალური პრობლემა დაგვანახა, რომელთაგან ერთ-ერთი არის განათლება. სწორედ ამიტომ, პრიორიტეტად პედაგოგიკის მიმართულება ავიღეთ.",
        "text4": "გადავწყვიტეთ, ვალდორფის პედაგოგიკის პრინციპებზე დაფუძნებული საგანმანათლებლო სივრცე აგვეშენებინა სოფელ მაწევანში (საქართველო).",
        "text5": "ჩვენი მთავარი მიზანია ხელი შევუწყოთ სხვადასხვა საგანმანათლებლო / სოციალური ინიციატივების დაგეგმვასა და განხორციელებას. სამომავლოდ გვინდა ამ სოფელში შევქმნათ საზოგადოება, სადაც თითოეული ინდივიდის საქმიანობა ორგანულად იქნება დაკავშირებული ერთმანეთთან.",
        "text6": "გაიგე მეტი"
    },
    "about": {
        "text": [
            "ისტორია",
            "ჩვენი ისტორია იწყება 2016 წელს. წლების განმავლობაში უამრავი იდეა დაიბადა, განხორციელდა ან გაუქმდა, მაგრამ გზამ, რომელიც აქამდე გამოვიარეთ მოგვიყვანა დღევანდელ დღემდე.",
            "ჯგუფის პირველი საქმიანობა მოიცავდა მრავალფეროვან მხატვრულ და სოციალურ აქტივობებს. მოვლენები 2020 წელს შეიცვალა. პანდემიამ ბევრი სოციალური პრობლემა დაგვანახა, რომელთაგან ერთ-ერთი არის განათლება. სწორედ ამიტომ, პრიორიტეტად პედაგოგიკის მიმართულება ავიღეთ. გადავწყვიტეთ, ვალდორფის განათლების პრინციპებზე დაფუძნებული საგანმანათლებლო სივრცე აგვეშენებინა სოფელ მაწევანში.",
            "დღეს ჩვენი მთავარი მიზანია ახალგაზრდების საგანმანათლებლო/სოციალური ინიციატივების დაგეგმვა, ხელშეწყობა და განხორციელება სხვადასხვა მიმართულებით. სამომავლოდ, გვინდა, ამ სოფელში შევქმნათ საზოგადოება, სადაც თითოეული ინდივიდის საქმიანობა ორგანულად იქნება ერთმანეთთან დაკავშირებული.",
            "რატომ პარსიფალი?",
            "სახელზე ბევრი არ გვიფიქრია - რაინდი პარსიფალი ჩვენთვის მნიშვნელოვანი პერსონაჟია.",
            "პარსიფალი არის ვოლფრამ ფონ ეშენბახის ეპიკური პოემის პერსონაჟი. ის იყო რაინდი, რომელმაც გრძელი და რთული გზა გაიარა, სანამ ჭეშმარიტებას, ღვთაებრივ სიბრძნეს და მაშასადამე ღმერთს იპოვიდა. პოემის მიხედვით, ის იყო წმინდა გრაალის უკანასკნელი მეფე და მცველი.",
            "ამ ამბით შთაგონებულმა რიჩარდ ვაგნერმა დაწერა ოპერა სახელწოდებით პარსიფალი, რომელიც მისი ბოლო კომპოზიცია იყო."
        ],
        "members": {
            "title": "ჩვენი გუნდი",
            "description": "ჩვენ ვართ მეგობართა ჯგუფი, რომელთაც გვაკავშირებს დიდი სურვილი, შევიტანოთ საზოგადოებაში ჯანსაღი იმპულსები. დღეისთვის ორგანიზაცია რამდენიმე პროექტზე მუშაობს. თითოეული პროექტის გარშემო კი გუნდის სხვადასხვა წევრები არიან გაერთიანებული.",
            "member": [
                {
                    "name": "სოფო ხადურიშვილი",
                    "description": "26 წლის. დაამთავრა ფსიქოლოგიისა და განათლების მეცნიერებათა ფაკულტეტი ბაკალავრის ხარისხით და აქვს მაგისტრის ხარისხი ორგანიზაციის განვითარებასა და კონსულტირებაში. ამჟამად ხელმძღვანელობს პარსიფალის საშაბათკვირაო სკოლას.",
                    "image": "/assets/images/about/img3.webp"
                },
                {
                    "name": "ანი ჯიბღაშვილი",
                    "description": "26 წლის. მას აქვს ბაკალავრის ხარისხი ეკონომიკაში და მაგისტრის ხარისხი ორგანიზაციის განვითარებასა და კონსულტაციაში. ამჟამად ხელმძღვანელობს პარსიფალის საშაბათკვირაო სკოლას.",
                    "image": "/assets/images/about/img4.webp"
                },
                {
                    "name": "ნიკოლოზ ყანჩაველი",
                    "description": "27 წლის. დაამთავრა სოციალურ და პოლიტიკურ მეცნიერებათა ფაკულტეტი ბაკალავრის ხარისხით და აქვს მაგისტრის ხარისხი ორგანიზაციის განვითარებასა და კონსულტირებაში. ამჟამად უძღვება პარსიფალის ახალგაზრდულ სემინარს.",
                    "image": "/assets/images/about/img5.webp"
                },
                {
                    "name": "ნათია ქობალია",
                    "description": "25 წლის. მას აქვს ბაკალავრის ხარისხი სოციალურ მეცნიერებებში. არის სოციალური მეცნიერების მასწავლებელი თბილისის კერძო სკოლაში. ასევე, ის ასწავლის თიხის ხელოვნებას პარსიფალის საშაბათკვირაო სკოლაში.",
                    "image": "/assets/images/about/img6.webp"
                },
                {
                    "name": "სოფიო გზირიშვილი",
                    "description": "23 წლის. აქვს ბაკალავრის ხარისხი ფსიქოლოგიაში. ამჟამად არის მასწავლებელი პარსიფალის სკოლაში. აქვს გამოცდილება აუტიზმის სპექტრისა და დაუნის სინდრომის მქონე ბავშვებთან მუშაობაში.",
                    "image": "/assets/images/about/img7.jpeg"
                },
                {
                    "name": "ბექა ქვრივიშვილი",
                    "description": "25 წლის. დაამთავრა სამშენებლო ფაკულტეტი. პარსიფალის საშაბათკვირაო სკოლაში ის ასწავლის ხელსაქმეს.",
                    "image": "/assets/images/about/img8.webp"
                },
                {
                    "name": "ნინია გოლიაძე",
                    "description": "28 წლის. დაამთავრა ფსიქოლოგიისა და განათლების მეცნიერებათა ფაკულტეტი ბაკალავრის ხარისხით. ამჟამად მუშაობს თბილისის თავისუფალ ვალდორფის სკოლაში კლასის მასწავლებლად. პარსიფალში იგი მუშაობს იპოთერაპიის პროექტზე.",
                    "image": "/assets/images/about/img9.webp"
                },
                {
                    "name": "გიორგი ექიზაშვილი",
                    "description": "27 წლის. მას აქვს ორი ბაკალავრის ხარისხი სამართალსა და ფსიქოლოგიაში. ის არის თერაპიული მასწავლებელი. პარსიფალში ის ხელმძღვანელობს იპოთერაპიის პროექტს.",
                    "image": "/assets/images/about/img10.webp"
                },
                {
                    "name": "ნინო კობაიძე",
                    "description": "27 წლის. დაამთავრა სამედიცინო ფაკულტეტი. დაინტერესებულია ანთროპოსოფიული მედიცინით. პარსიფალში მუშაობს იპოთერაპიის პროექტის მიმართულებით.",
                    "image": "/assets/images/about/img11.webp"
                },
                {
                    "name": "ილია დუნდუა",
                    "description": "26 წლის. მას აქვს ბაკალავრის ხარისხი ფსიქოლოგიასა და განათლების მეცნიერებანი. პარსიფალში პასუხისმგებელია ლოჯისტიკაზე.",
                    "image": "/assets/images/about/img12.webp"
                },
                {
                    "name": "მარიამ კვირტია",
                    "description": "26 წლის. დაამთავრა ფსიქოლოგიისა და განათლების მეცნიერებათა ფაკულტეტი. ამჟამად სწავლობს გერმანიაში.",
                    "image": "/assets/images/about/img13.webp"
                },
                {
                    "name": "დავით ქვრივიშვილი",
                    "description": "27 წლის. დაამთავრა არქიტექტურის ფაკულტეტი. ამჟამად სწავლობს გერმანიაში.",
                    "image": "/assets/images/about/img14.webp"
                }
            ]
        }
    },
    "school": {
        "schoolNav": [
            {
                "name": "მეთოდოლოგია",
                "href": "/projects/school#one"
            },
            {
                "name": "სასწავლო პროცესი",
                "href": "/projects/school#two"
            },
            {
                "name": "ჯგუფები",
                "href": "/projects/school#three"
            },
            {
                "name": "დამატებითი პროექტები",
                "href": "/projects/school#four"
            },
            {
                "name": "გალერეა",
                "href": "/projects/school#five"
            }
        ],
        "text1": [
            "პარსიფალის საშაბათკვირაო სკოლა",
            "პარსიფალის საშაბათკვირაო სკოლა არის ჩვენი ჯგუფის პირველი წარმატებული პროექტი. სკოლამ ფუნქციონირება 2022 წლის ოქტომბერში დაიწყო. მისი მთავარი დანიშნულებაა, დაეხმარეოს 9-დან 14 წლამდე  მოზარდებს პიროვნული უნარების განვითარებაში.",
            "პარსიფალის სკოლის მოსწავლეები იღებენ ალტერნატიულ განათლებას, მონაწილეობენ კულტურულ ღონისძიებებში და საფუძვლიანად ეცნობიან სხვადასხვა სფეროს.",
            "რეგისტრაცია"
        ],
        "text2": [
            "მეთოდოლოგია და იდეოლოგია",
            "ჩვენ გვჯერა, რომ პედაგოგიკა ადამიანის განვითარების ერთ-ერთი ყველაზე ღირსეული სამარჯვია. ბავშვისთვის სწორი საგანმანათლებლო სივრცე უაღრესად მნიშვნელოვანია და ის განსაზღვრავს მის მომავალ ცხოვრებას.",
            "ჩვენ ვიზიარებთ და მივყვებით ვალდორფის პედაგოგიკას. ეს მიდგომა ეფუძნება თვითრეალიზაციის გზით სწავლის პროცესს, რომელიც ითვალისწინებს პიროვნების ფიზიკურ, სოციალურ, ემოციურ და სულიერ ზრდას კომპლექსურად",
            "საგანმანათლებლო სილაბუსის შემუშავების ფაზაში და მოსწავლეებთან ურთიერთობისას, პედაგოგიური ჯგუფი ეყრდნობა ანთროპოსოფიულ კვლევებს ადამიანის განვითარების შესახებ. სხვადასხვა თემების გაცნობისას მოსწავლეები ეცნობიან საკითხს, არა მხოლოდ თეორიული მიმართულებით, არამედ ეს ცოდნა გადააქვთ პრაქტიკულ მუშაობაში, ხელსაქმის გაკვეთილის დახმარებით."
        ],
        "text3": [
            "სასწავლო პროცესი",
            "წლის განმავლობაში სასწავლო პროცესი იყოფა სამ ეპოქად: შემოდგომა-ზამთრის, ზამთარ-გაზაფხულისა და გაზაფხულ-ზაფხულის ეპოქა. თითოეული ეპოქის განმავლობაში სასწავლო საგნები ირჩევა სეზონის ხასიათისა და მოსწავლეების ფსიქო-სოციალური განვითარების მიხედვით.",
            "მივყვებით სწავლების პროექტულ სტილს. ეპოქის განმავლობაში ვირჩევთ  ერთ დიდ პროქტს, რომლის განხორციელების პროცესშიც ვსწავლობთ ყველაფერს, რაც მიზნის მისაღწევადაა საჭირო.",
            "პროგრამის დეტალური აღწერა"
        ],
        "text4": [
            "ჯგუფები და პროგრამები",
            "ამ დროისთვის სკოლაში არსებობს ორი ასაკობრივი ჯგუფი, 8-10 წლის და 11-დან 14 წლის მოსწავლეთა ჯგუფი. მოსწავლეები მიიღებიან ყოველი  ტრიმესტრის დასაწყისში, რეგისტრაციის საფუძველზე (სექტემბრის, იანვრის და აპრილის თვეებში).",
            "გარდა ამისა, მოსწავლეების ინტერესებისა და საჭიროებების გათვალისწინებით, ვქმნით სხვადასხვა თემატურ კლუბებს. აღნიშნული წრეები ორიენტირებულია მოზარდების ლოგიკური და ანალიტიკური უნარების განვითარებაზე. ამ დროისთვის, შექმნილია სამაგიდო თამაშების კლუბი  და მომავალში ვაპირებთ სხვა თემატური წრეების დამატებას.",
            "სამაგიდო თამაშების კლუბში გაწევრიანება"
        ]
    }
}